xcrap_parser/__init__.py
xcrap_parser/html_parser.py
xcrap_parser/html_parsing_model.py
xcrap_parser/json_parser.py
xcrap_parser/json_parsing_model.py
xcrap_parser/parser.py
xcrap_parser/parsing_model.py
xcrap_parser-0.1.1.dist-info/METADATA
xcrap_parser-0.1.1.dist-info/WHEEL
xcrap_parser-0.1.1.dist-info/RECORD
